graphene_field_permission/__init__.py
graphene_field_permission/api.py
graphene_field_permission/decorators.py
graphene_field_permission/fixtures.py
graphene_field_permission/permissions.py
graphene_field_permission/permissions_loader.py
graphene_field_permission/tests/__init__.py
graphene_field_permission/tests/fixtures.py
graphene_field_permission/tests/test_api.py
graphene_field_permission/tests/test_decorators.py
graphene_field_permission/tests/test_fixtures.py
graphene_field_permission/tests/test_permissions.py
graphene_field_permission/tests/test_permissions_loader.py
graphene_field_permission-1.1.0.dist-info/LICENSE
graphene_field_permission-1.1.0.dist-info/METADATA
graphene_field_permission-1.1.0.dist-info/WHEEL
graphene_field_permission-1.1.0.dist-info/top_level.txt
graphene_field_permission-1.1.0.dist-info/RECORD
