Metadata-Version: 2.1
Name: graphene-field-permission
Version: 1.1.0
Summary: A package to add field permission support for Graphene
Home-page: https://github.com/daveoconnor/graphene-field-permission
Author: Dave O'Connor
Author-email: github@dead-pixels.org
License: UNKNOWN
Platform: UNKNOWN
Classifier: Programming Language :: Python :: 3
Classifier: Programming Language :: Python :: 3.7
Classifier: Programming Language :: Python :: 3.8
Classifier: Programming Language :: Python :: 3.9
Classifier: Programming Language :: Python :: 3.10
Classifier: License :: OSI Approved :: MIT License
Classifier: Operating System :: OS Independent
